mlconfgen/__init__.py
mlconfgen/adj_mat_seer.py
mlconfgen/conformer_generator.py
mlconfgen/conformer_generator_onnx.py
mlconfgen/egnn.py
mlconfgen/equivariant_diffusion.py
mlconfgen/equivariant_diffusion_onnx.py
mlconfgen/cheminformatics/__init__.py
mlconfgen/cheminformatics/pipeline.py
mlconfgen/cheminformatics/shape_similarity.py
mlconfgen/utils/__init__.py
mlconfgen/utils/config.py
mlconfgen/utils/mol_utils.py
mlconfgen/utils/molgraph.py
mlconfgen/utils/onnx_utils.py
mlconfgen/utils/standardizer.py
mlconfgen-0.2.2.dist-info/licenses/LICENSE
mlconfgen-0.2.2.dist-info/licenses/LICENSE-MODEL
mlconfgen-0.2.2.dist-info/METADATA
mlconfgen-0.2.2.dist-info/WHEEL
mlconfgen-0.2.2.dist-info/top_level.txt
mlconfgen-0.2.2.dist-info/RECORD
