Metadata-Version: 2.4
Name: mlconfgen
Version: 0.2.2
Summary: Shape-constrained molecule generation via Equivariant Diffusion and GCN
Author-email: Denis Sapegin <dasapegin@gmail.com>, Fedor Bakharev <fbakharev@gmail.com>, Azamat Gafurov <azamat.gafurov@gmail.com>
Maintainer-email: Denis Sapegin <dasapegin@gmail.com>, Azamat Gafurov <azamat.gafurov@gmail.com>
License-Expression: CC-BY-NC-ND-4.0 AND Apache-2.0
Project-URL: Homepage, https://github.com/Membrizard/ml_conformer_generator
Project-URL: Issues, https://github.com/Membrizard/ml_conformer_generator/issues
Keywords: rdkit,chemistry,diffusion,conformers
Classifier: Development Status :: 3 - Alpha
Classifier: Programming Language :: Python :: 3
Classifier: Programming Language :: Python :: 3.10
Classifier: Programming Language :: Python :: 3.11
Classifier: Programming Language :: Python :: 3.12
Classifier: Operating System :: OS Independent
Classifier: Topic :: Scientific/Engineering :: Chemistry
Requires-Python: >=3.10
License-File: LICENSE
License-File: LICENSE-MODEL
Requires-Dist: torch>=2.0.1
Requires-Dist: rdkit>=2023.9.5
Requires-Dist: numpy>=1.26.4
Provides-Extra: onnx
Requires-Dist: onnx>=1.17.0; extra == "onnx"
Requires-Dist: onnxruntime>=1.19.0; extra == "onnx"
Requires-Dist: onnxscript>=0.2.0; extra == "onnx"
Dynamic: license-file
